pimp_my_repo/__init__.py
pimp_my_repo/main.py
pimp_my_repo-0.1.0.dist-info/METADATA
pimp_my_repo-0.1.0.dist-info/WHEEL
pimp_my_repo-0.1.0.dist-info/RECORD
