Metadata-Version: 2.1
Name: pimp-my-repo
Version: 0.1.0
Summary: pimp-my-repo is an open-source tool designed to enhance your Python repositories by adding essential development tools and configurations. It automates the setup of linting and formatting tools, pre-commit hooks, a Makefile with basic commands, and Poetry for dependency management.
Author: Asaf Kali
Author-email: asaf.kali@mail.huji.ac.il
Requires-Python: >=3.11,<4.0
Classifier: Programming Language :: Python :: 3
Classifier: Programming Language :: Python :: 3.11
Classifier: Programming Language :: Python :: 3.12
Project-URL: Homepage, https://github.com/asaf-kali/pimp-my-repo
Project-URL: Issues, https://github.com/asaf-kali/pimp-my-repo/issues
Project-URL: Repository, https://github.com/asaf-kali/pimp-my-repo
